deprecat/__init__.py
deprecat/backends/__init__.py
deprecat/backends/models.py
deprecat/backends/server.py
deprecat/backends/utils.py
deprecat/cli/__init__.py
deprecat/cli/__main__.py
deprecat/cli/analyze.py
deprecat/cli/app.py
deprecat/cli/doctor.py
deprecat/cli/review.py
deprecat/cli/scan.py
deprecat/cli/serve.py
deprecat/cli/show.py
deprecat/core/__init__.py
deprecat/core/config.py
deprecat/core/dependencies.py
deprecat/core/paths.py
deprecat/core/settings.py
deprecat/indexer/__init__.py
deprecat/scanner/__init__.py
deprecat/scanner/context.py
deprecat/scanner/indexer.py
deprecat/scheduler/__init__.py
deprecat_agent-0.1.3.dist-info/METADATA
deprecat_agent-0.1.3.dist-info/WHEEL
deprecat_agent-0.1.3.dist-info/entry_points.txt
deprecat_agent-0.1.3.dist-info/licenses/LICENSE
deprecat_agent-0.1.3.dist-info/RECORD
