Metadata-Version: 2.4
Name: deprecat-agent
Version: 0.1.3
Summary: CLI toolkit for scanning TPAs
License: MIT License
License-File: LICENSE
Requires-Python: >=3.11
Requires-Dist: fastapi>=0.110
Requires-Dist: httpx>=0.27
Requires-Dist: pydantic-settings>=2.2
Requires-Dist: pydantic>=2.6
Requires-Dist: rich>=13.7
Requires-Dist: typer>=0.12.3
Requires-Dist: uvicorn>=0.29
Provides-Extra: dev
Requires-Dist: pytest-cov>=5.0; extra == 'dev'
Requires-Dist: pytest>=8.1; extra == 'dev'
Requires-Dist: ruff>=0.4.1; extra == 'dev'
